bs_lib/__init__.py
bs_lib/auto_transaction.py
bs_lib/auto_transaction_async.py
bs_lib/common.py
bs_lib/iprovider.py
bs_lib/pod.py
bs_lib/pod_async.py
bs_lib/provider_std.py
bs_lib/query_builder.py
bs_lib/sentinel_manager.py
bs_lib/sentinel_process.py
bs_lib/sentinel_thread.py
bs_lib/transactionable.py
bs_lib/transactionable_async.py
bitsmiths_lib-2.1.4.dist-info/LICENCE
bitsmiths_lib-2.1.4.dist-info/METADATA
bitsmiths_lib-2.1.4.dist-info/WHEEL
bitsmiths_lib-2.1.4.dist-info/top_level.txt
bitsmiths_lib-2.1.4.dist-info/RECORD
