Metadata-Version: 2.1
Name: bitsmiths-lib
Version: 2.1.4
Summary: The Bitsmiths core central business library that all other Bitsmiths Products are built upon.
Home-page: https://bitbucket.org/bitsmiths_za/bitsmiths
Author: Nicolas Milicevic, Steven van Niekerk, Darrly Daniels
Author-email: nicolas@bitsmiths.co.za, steven@bitsmiths.co.za, darryl@bitsmiths.co.za
License: MIT
Project-URL: Source, https://bitbucket.org/bitsmiths_za/bitsmiths
Keywords: libraries
Platform: unix
Platform: linux
Platform: osx
Platform: cygwin
Platform: win32
Classifier: Development Status :: 5 - Production/Stable
Classifier: Intended Audience :: Developers
Classifier: License :: OSI Approved :: MIT License
Classifier: Operating System :: MacOS :: MacOS X
Classifier: Operating System :: POSIX
Classifier: Programming Language :: Python :: 3
Classifier: Programming Language :: Python :: 3.7
Classifier: Programming Language :: Python :: 3.8
Classifier: Programming Language :: Python :: 3.9
Classifier: Programming Language :: Python :: 3 :: Only
Classifier: Topic :: Software Development :: Libraries
Classifier: Topic :: Software Development :: Libraries :: Python Modules
Requires-Python: >=3.7
License-File: LICENCE
Requires-Dist: bitsmiths-mettle (>=2.1.0)
